dmr_utils3/__init__.py
dmr_utils3/ambe.py
dmr_utils3/ambe_utils.py
dmr_utils3/bptc.py
dmr_utils3/const.py
dmr_utils3/crc.py
dmr_utils3/decode.py
dmr_utils3/encode.py
dmr_utils3/golay.py
dmr_utils3/golay_tables.py
dmr_utils3/hamming.py
dmr_utils3/qr.py
dmr_utils3/rs129.py
dmr_utils3/utils.py
dmr_utils3-0.1.29.dist-info/LICENSE
dmr_utils3-0.1.29.dist-info/METADATA
dmr_utils3-0.1.29.dist-info/WHEEL
dmr_utils3-0.1.29.dist-info/top_level.txt
dmr_utils3-0.1.29.dist-info/RECORD
