Metadata-Version: 2.1
Name: dmr-utils3
Version: 0.1.29
Summary: ETSI DMR (Digital Mobile Radio) Tier II Utilities
Home-page: https://github.com/n0mjs710/dmr_utils
Author: Cortney T. Buffington, N0MJS
Author-email: n0mjs@me.com
License: GPLv3
Keywords: dmr radio digital fec ecc mmdvm ham amateur radio
Platform: UNKNOWN
Classifier: License :: OSI Approved :: GNU General Public License v3 or later (GPLv3+)
Classifier: Development Status :: 5 - Production/Stable
Classifier: Programming Language :: Python :: 3.5
Classifier: Natural Language :: English
Classifier: Operating System :: OS Independent
Classifier: Topic :: Communications :: Ham Radio
Classifier: Topic :: Software Development :: Libraries :: Python Modules
Classifier: Topic :: Utilities
Requires-Dist: bitstring (>=3.1.5)
Requires-Dist: bitarray (>=0.8.3)
